Metadata-Version: 1.0
Name: pyperseo
Version: 0.0.9
Summary: Personal Semantic Objects
Home-page: https://github.com/pabloalarconm/PERSEO
Author: Pablo Alarcón Moreno
Author-email: pabloalarconmoreno@gmail.com
License: MIT
Keywords: Semantic,RDF,FAIR,EJP
Platform: UNKNOWN
